{
  "app": {
    "[project]/apps/frontend/src/app/(shell)/copilot/page": [
      "static/media/caa3a2e1cccd8315-s.p.853070df.woff2",
      "static/media/797e433ab948586e-s.p.dbea232f.woff2"
    ],
    "[project]/apps/frontend/src/app/(shell)/inventory/page": [
      "static/media/caa3a2e1cccd8315-s.p.853070df.woff2",
      "static/media/797e433ab948586e-s.p.dbea232f.woff2"
    ],
    "[project]/apps/frontend/src/app/(shell)/pos/page": [
      "static/media/caa3a2e1cccd8315-s.p.853070df.woff2",
      "static/media/797e433ab948586e-s.p.dbea232f.woff2"
    ],
    "[project]/apps/frontend/src/app/(shell)/reports/page": [
      "static/media/caa3a2e1cccd8315-s.p.853070df.woff2",
      "static/media/797e433ab948586e-s.p.dbea232f.woff2"
    ],
    "[project]/apps/frontend/src/app/(shell)/settings/page": [
      "static/media/caa3a2e1cccd8315-s.p.853070df.woff2",
      "static/media/797e433ab948586e-s.p.dbea232f.woff2"
    ],
    "[project]/apps/frontend/src/app/_not-found/page": [
      "static/media/caa3a2e1cccd8315-s.p.853070df.woff2",
      "static/media/797e433ab948586e-s.p.dbea232f.woff2"
    ],
    "[project]/apps/frontend/src/app/auth/sign-in/[[...rest]]/page": [
      "static/media/caa3a2e1cccd8315-s.p.853070df.woff2",
      "static/media/797e433ab948586e-s.p.dbea232f.woff2"
    ],
    "[project]/apps/frontend/src/app/onboarding/page": [
      "static/media/caa3a2e1cccd8315-s.p.853070df.woff2",
      "static/media/797e433ab948586e-s.p.dbea232f.woff2"
    ],
    "[project]/apps/frontend/src/app/page": [
      "static/media/caa3a2e1cccd8315-s.p.853070df.woff2",
      "static/media/797e433ab948586e-s.p.dbea232f.woff2"
    ]
  },
  "appUsingSizeAdjust": true,
  "pages": {},
  "pagesUsingSizeAdjust": false
}